.coveragerc
.testr.conf
AUTHORS
ChangeLog
LICENSE
MANIFEST.in
README.rst
requirements.txt
setup.cfg
setup.py
test-requirements.txt
tox.ini
doc/source/conf.py
doc/source/contributing.rst
doc/source/index.rst
doc/source/installation.rst
doc/source/readme.rst
doc/source/usage.rst
rally_runners/__init__.py
rally_runners/utils.py
rally_runners.egg-info/PKG-INFO
rally_runners.egg-info/SOURCES.txt
rally_runners.egg-info/dependency_links.txt
rally_runners.egg-info/entry_points.txt
rally_runners.egg-info/not-zip-safe
rally_runners.egg-info/pbr.json
rally_runners.egg-info/requires.txt
rally_runners.egg-info/top_level.txt
rally_runners/reliability/__init__.py
rally_runners/reliability/analytics.py
rally_runners/reliability/graphics.py
rally_runners/reliability/report.py
rally_runners/reliability/runner.py
rally_runners/reliability/types.py
rally_runners/reliability/rally_plugins/__init__.py
rally_runners/reliability/rally_plugins/fault_injection.py
rally_runners/reliability/scenarios/keystone/authenticate_with_kill_keystone_service_on_one_node.yaml
rally_runners/reliability/scenarios/keystone/authenticate_with_kill_mysql_service_on_one_node.yaml
rally_runners/reliability/scenarios/keystone/authenticate_with_restart_keystone_service_on_one_node.yaml
rally_runners/reliability/scenarios/keystone/authenticate_with_restart_memcached_service_on_one_node.yaml
rally_runners/reliability/scenarios/neutron/create_and_list_networks_with_kill_mysql_service_on_one_node.yaml
rally_runners/reliability/scenarios/nova/boot_and_delete_with_disconnect_management_network_on_one_node_with_nova_scheduler_service.yaml
rally_runners/reliability/scenarios/nova/boot_and_delete_with_disconnect_storage_network_on_one_node_with_nova_compute_service.yaml
rally_runners/reliability/scenarios/nova/boot_and_delete_with_kill_mysql_service_on_one_node.yaml
rally_runners/reliability/scenarios/nova/boot_and_delete_with_kill_rabbitmq_service_on_one_node.yaml
rally_runners/reliability/scenarios/nova/boot_and_delete_with_reboot_one_node_with_rabbitmq_service.yaml
rally_runners/reliability/scenarios/nova/list_flavors_with_restart_keystone_service_on_one_node.yaml
rally_runners/reliability/scenarios/vm/boot_run_command_delete_with_restart_keystone_service_on_one_node.yaml
